{
  "welcome": "Welcome (english)",
  "language": "Language",
  "nav-home": "Home",
  "nav-config": "Configuration",
  "nav-system": "System",
  "nav-devices": "Devices",
  "nav-gateways": "Gateways",
  "nav-meter": "Meter",
  "nav-LoRa": "LoRa",
  "nav-upload": "Upload",
  "nav-download": "Download",
  "nav-status": "Status",
  "nav-sessions": "Sessions",
  "nav-targets": "Targets",
  "nav-connections": "Connections",
  "nav-monitoring": "Monitoring",
  "nav-messages": "Messages",
  "nav-tsdb": "Time Series",
  "nav-lora-uplink": "LoRa Uplink",
  "nav-tasks": "Tasks",
  "nav-plausibility": "Plausibility",
  "state-online": "online",
  "state-offline": "offline",
  "state-mounted": "mounted",
  "header-dashboard": "Your SMF dashboard",
  "lead-dashboard": "Start managing your Smart Metering Framework",
  "header-system": "Configure your System %{version}",
  "lead-system": "%{node} is the current master node",
  "header-device": "Device Management",
  "lead-device": "%{count} devices at a glance",
  "header-gateway": "Gateway Management",
  "lead-gateway": "%{count} gateways at a glance",
  "header-meter": "Meter Management",
  "lead-meter": "%{count} meters at a glance",
  "header-LoRa": "LoRa Gateway Management",
  "lead-LoRa": "%{count} LoRa gateways at a glance",
  "header-upload": "Upload Configuration Files",
  "lead-upload": "Restore or enlarge the system configuration",
  "header-download": "Download Configuration Files",
  "lead-download": "Backup or transfer the system configuration",
  "header-status-session": "All subscribers that are online",
  "lead-status-session": "%{count} sessions so far",
  "header-status-targets": "Registered push targets",
  "lead-status-targets": "%{count} targets registered",
  "header-status-connections": "Running dial-up connections",
  "lead-status-connections": "%{count} connection(s) so far",
  "header-monitor-system": "System Status",
  "lead-monitor-system": "%{count} nodes online",
  "header-monitor-messages":"System Messages",
  "lead-monitor-messages":"%{count} messages logged",
  "header-monitor-tsdb":"Time Series",
  "header-monitor-lora":"LoRa Uplink",
  "lead-monitor-lora":"%{count} uplinks stored",
  "header-task-csv":"Generate CSV reports",
  "lead-task-csv-0":"no CSV reporter ",
  "lead-task-csv-1":"There is one node that creates CSV reports",
  "header-task-tsdb":"Bridge to Time Series Databases",
  "lead-task-tsdb":"%{count} time series databases online",
  "header-task-plausibility":"Test plausibility",
  "config-sys-01": "Auto Login",
  "config-sys-02": "Accept unknown devices and transfer the login data to the configuration database (not recommended).",
  "config-sys-02-1": "default = ",
  "config-sys-03": "Auto Enabled",
  "config-sys-04": "Set automatically configured devices as enabled.",
  "config-sys-04-1": "default = ",
  "config-sys-05": "supersede",
  "config-sys-06": "New login terminates running session with same credentials (recommended)",
  "config-sys-06-1": "default = ",
  "config-sys-07": "Country Code",
  "config-sys-07-1": "default = ",
  "config-sys-08": "Language Code",
  "config-sys-08-1": "default = ",
  "config-sys-09": "System Messages",
  "config-sys-09-1": "default",
  "config-sys-09-2": "Commit",
  "config-sys-09-3": "default = ",
  "config-sys-10": "System Events",
  "config-sys-10-1": "Default",
  "config-sys-10-2": "Commit",
  "config-sys-10-3": "default = ",
  "config-sys-11": "Generate Time-Series",
  "config-sys-12": "write statistics into",
  "config-sys-13": " (This may have a performance impact).",
  "config-sys-13-1": "default = ",
  "config-sys-14": "Catch new Meters",
  "config-sys-15": "Catch new meters during gateway configuration.",
  "config-sys-15-1": "default = ",
  "config-sys-16": "Catch new LoRa Devices",
  "config-sys-17": "Insert unkown LoRa devices automatically",
  "config-sys-17-1": "default = "
}
